rawpython/__init__.py
rawpython/color/__init__.py
rawpython/color/color.py
rawpython/pbar/__init__.py
rawpython/pbar/pbar.py
rawpython-0.1.dist-info/METADATA
rawpython-0.1.dist-info/WHEEL
rawpython-0.1.dist-info/top_level.txt
rawpython-0.1.dist-info/RECORD
