Metadata-Version: 2.1
Name: rawpython
Version: 0.1
Summary: a library for people who hate libraries
Author: Diego Llanes
Author-email: rawpython@diegollanes.com
License: UNKNOWN
Platform: UNKNOWN
